genkit/codec.py
genkit/py.typed
genkit/testing.py
genkit/ai/__init__.py
genkit/ai/plugin.py
genkit/ai/registry.py
genkit/ai/server.py
genkit/ai/veneer.py
genkit/aio/__init__.py
genkit/aio/_util.py
genkit/aio/channel.py
genkit/aio/loop.py
genkit/blocks/__init__.py
genkit/blocks/document.py
genkit/blocks/embedding.py
genkit/blocks/generate.py
genkit/blocks/messages.py
genkit/blocks/middleware.py
genkit/blocks/model.py
genkit/blocks/prompt.py
genkit/blocks/retriever.py
genkit/blocks/tools.py
genkit/blocks/formats/__init__.py
genkit/blocks/formats/json.py
genkit/blocks/formats/types.py
genkit/core/__init__.py
genkit/core/constants.py
genkit/core/environment.py
genkit/core/error.py
genkit/core/extract.py
genkit/core/flows.py
genkit/core/reflection.py
genkit/core/registry.py
genkit/core/schema.py
genkit/core/status_types.py
genkit/core/tracing.py
genkit/core/typing.py
genkit/core/action/__init__.py
genkit/core/action/_action.py
genkit/core/action/_key.py
genkit/core/action/_tracing.py
genkit/core/action/_util.py
genkit/core/action/types.py
genkit/lang/__init__.py
genkit/lang/deprecations.py
genkit/plugins/.gitignore
genkit/types/__init__.py
genkit/web/__init__.py
genkit/web/requests.py
genkit/web/typing.py
genkit/web/manager/__init__.py
genkit/web/manager/_adapters.py
genkit/web/manager/_base_server.py
genkit/web/manager/_info.py
genkit/web/manager/_loop.py
genkit/web/manager/_manager.py
genkit/web/manager/_ports.py
genkit/web/manager/_server.py
genkit/web/manager/signals.py
genkit_ai-0.0.1.dev1.dist-info/METADATA
genkit_ai-0.0.1.dev1.dist-info/WHEEL
genkit_ai-0.0.1.dev1.dist-info/licenses/LICENSE
genkit_ai-0.0.1.dev1.dist-info/RECORD
